ducts/__init__.py
ducts/__main__.py
ducts/app.py
ducts/auth.py
ducts/common.py
ducts/context.py
ducts/event.py
ducts/mixin.py
ducts/redis.py
ducts/server.py
ducts/spi.py
ducts/assets/favicon.ico
ducts/assets/jsonp_template.js
ducts/backend/__init__.py
ducts/backend/asr.py
ducts/handler/__init__.py
ducts/handler/evt_0000_alive_monitoring.py
ducts/handler/evt_0001_loop_response_start.py
ducts/handler/evt_0002_loop_response_next.py
ducts/handler/evt_0003_loop_response_end.py
ducts/handler/evt_0004_divided_response_append.py
ducts/handler/evt_0005_divided_response_end.py
ducts/handler/evt_0100_logging.py
ducts/handler/evt_0200_ping.py
ducts/handler/evt_0300_redis_execute.py
ducts/handler/evt_0400_events.py
ducts/handler/evt_0500_blobs.py
ducts/handler/evt_0510_blobs_group_list.py
ducts/handler/evt_0511_blobs_group_versions.py
ducts/handler/evt_0512_blobs_group_metadata.py
ducts/handler/evt_0513_blobs_group_exists.py
ducts/handler/evt_0514_blobs_group_list_names.py
ducts/handler/evt_0521_blobs_group_add.py
ducts/handler/evt_0522_blobs_group_update.py
ducts/handler/evt_0529_blobs_group_delete.py
ducts/handler/evt_0530_blobs_content_list.py
ducts/handler/evt_0531_blobs_content_versions.py
ducts/handler/evt_0532_blobs_content_metadata.py
ducts/handler/evt_0533_blobs_content_exists.py
ducts/handler/evt_0534_blobs_content_is_dir.py
ducts/handler/evt_0535_blobs_content_filter.py
ducts/handler/evt_0541_blobs_content_add.py
ducts/handler/evt_0542_blobs_content_add_by_buffer.py
ducts/handler/evt_0543_blobs_content_add_dir.py
ducts/handler/evt_0551_blobs_content_update.py
ducts/handler/evt_0552_blobs_content_update_by_buffer.py
ducts/handler/evt_0560_blobs_content_revert.py
ducts/handler/evt_0571_blobs_dir_add_files.py
ducts/handler/evt_0572_blobs_dir_list_files.py
ducts/handler/evt_0573_blobs_dir_file_metadata.py
ducts/handler/evt_0574_blobs_dir_file_exists.py
ducts/handler/evt_0579_blobs_dir_rm_files.py
ducts/handler/evt_0590_blobs_buffer_open.py
ducts-0.1.7.dist-info/METADATA
ducts-0.1.7.dist-info/WHEEL
ducts-0.1.7.dist-info/top_level.txt
ducts-0.1.7.dist-info/RECORD
