Metadata-Version: 2.1
Name: ducts
Version: 0.1.7
Summary: DUplex Communication and Transactional Streaming Web Framework
Home-page: https://github.com/iflb/ducts
Author: teppei@iflab.tokyo
Author-email: teppei@iflab.tokyo
License: UNKNOWN
Project-URL: Project Owner, http://www.pcl.cs.waseda.ac.jp/
Project-URL: Funding, https://www.waseda.jp/inst/gcs/news/2019/11/29/870/
Keywords: framework asyncio websocket
Platform: UNKNOWN
Classifier: Development Status :: 2 - Pre-Alpha
Classifier: Intended Audience :: Developers
Classifier: Framework :: AsyncIO
Classifier: License :: OSI Approved :: MIT License
Classifier: Programming Language :: Python :: 3
Classifier: Operating System :: OS Independent
Requires-Python: >=3.6
Requires-Dist: iflb (<0.1,>=0.0.1)
Requires-Dist: ifconf (<0.1,>=0.0.15)
Requires-Dist: msgpack (<2,>=1.0)
Requires-Dist: aiofiles (<0.9,>=0.8.0)
Requires-Dist: aiohttp (<4,>=3.8)
Requires-Dist: aiohttp-remotes (<2,>=1.2)
Requires-Dist: aioredis (<2,>=1)
Requires-Dist: async-timeout (<5,>=4.0)
Requires-Dist: python-daemon (<3,>=2.3)
Requires-Dist: psutil (<6,>=5.9)
Requires-Dist: wave (<0.1,>=0.0.2)
